[
  {
    "schema": null,
    "name": "spo-list-site-externalusers",
    "version": null,
    "source": "pnp",
    "title": "List all external users in all site collections",
    "url": "spo-list-site-externalusers/README.html",
    "creationDateTime": "2021-03-15",
    "updateDateTime": "2021-03-15",
    "shortDescription": "Script helps you to list all external users in all SharePoint Online sites",
    "longDescription": null,
    "products": [
      "SharePoint"
    ],
    "categories": [
      "Report"
    ],
    "tags": [
      "SharePoint Online",
      "Governance",
      "External Users"
    ],
    "metadata": [
      {
        "key": "cli-for-microsoft365",
        "value": "3.7.0"
      }
    ],
    "thumbnails": [
      {
        "type": "image",
        "order": 100,
        "url": "spo-list-site-externalusers/assets/preview.png",
        "alt": "preview image for the sample",
        "slides": null
      }
    ],
    "authors": [
      {
        "name": "Albert-Jan Schot",
        "gitHubAccount": "appieschot",
        "company": "@portiva",
        "pictureUrl": "https://avatars.githubusercontent.com/u/15227781?v=4"
      }
    ],
    "references": null
  }
]