[
    {
      "name": "spo-generate-demo-events",
      "source": "pnp",
      "title": "Generate Demo Events for SharePoint Events List",
      "shortDescription": "This sample script generates demo events for the SharePoint Events List within a modern site using a CSV file",
      "url": "spo-generate-demo-events/README.html",
      "longDescription": [],
      "creationDateTime": "2021-09-08",
      "updateDateTime": "2021-10-10",
      "products": [
        "SharePoint"
      ],
      "metadata": [
        {
          "key": "pnp-powerShell",
          "value": "1.7.0"
        },
        {
          "key": "cli-for-microsoft365",
          "value": "3.7.0"
        }
      ],
      "categories": [
        "Data"
      ],
      "tags":[
        "modern"
      ],
      "thumbnails": [
        {
          "type": "image",
          "order": 100,
          "url": "spo-generate-demo-events/assets/preview.png",
          "alt": ""
        }
      ],
      "authors": [
        {
          "gitHubAccount": "Adam-it",
          "pictureUrl": "https://avatars.githubusercontent.com/u/58668583?v=4",
          "name": "Adam Wójcik"
        },
        {
          "gitHubAccount": "pkbullock",
          "company": "CPS Group Ltd",
          "pictureUrl": "https://avatars.githubusercontent.com/u/8781041?v=4",
          "name": "Paul Bullock"
        }
      ]
    }
  ]