[
  {
    "name": "spo-get-items-with-custom-permissions",
    "source": "pnp",
    "title": "Find all items with unique permissions and export to csv",
    "shortDescription": "Find items where the permissions have been broken",
    "url": "https://pnp.github.io/script-samples/spo-get-items-with-custom-permissions/README.html",
    "longDescription": [
      ""
    ],
    "creationDateTime": "2023-05-10",
    "updateDateTime": "2023-05-10",
    "products": [
      "SharePoint"
    ],
    "metadata": [
      {
        "key": "PNP-POWERSHELL",
        "value": "2.1.1"
      }
    ],
    "categories": [
      "Report",
      "Security"
    ],
    "tags": [
      "Connect-PnPOnline",
      "Get-PnPList",
      "Get-PnPListItem",
      "Get-PnPProperty",
      "Get-PnPSubWeb",
      "Get-PnPTenant",
      "Get-PnPTenantSite"
    ],
    "thumbnails": [
      {
        "type": "image",
        "order": 100,
        "url": "https://raw.githubusercontent.com/pnp/script-samples/main/scripts/spo-get-items-with-custom-permissions/assets/preview.png",
        "alt": "Preview of the sample Find all items with unique permissions and export to csv"
      }
    ],
    "authors": [
      {
        "gitHubAccount": "kasperbolarsen",
        "company": "",
        "pictureUrl": "https://github.com/kasperbolarsen.png",
        "name": "Kasper Larsen"
      }
    ],
    "references": [
      {
        "name": "Want to learn more about PnP PowerShell and the cmdlets",
        "description": "Check out the PnP PowerShell site to get started and for the reference to the cmdlets.",
        "url": "https://aka.ms/pnp/powershell"
      }
    ]
  }
]
