[
  {
    "name": "azure-devops-clone-all-repositories",
    "source": "pnp",
    "title": "Clone all repositories from Azure DevOps",
    "shortDescription": "A secure, user-friendly PowerShell script to clone all accessible Git repositories from an Azure DevOps organization",
    "url": "https://pnp.github.io/script-samples/azure-devops-clone-all-repositories/README.html",
    "longDescription": [""],
    "creationDateTime": "2025-10-29",
    "updateDateTime": "2025-10-29",
    "products": ["Azure"],
    "metadata": [
      {
        "key": "AZURE-CLI",
        "value": "2.27.0"
      }
    ],
    "categories": ["Configure"],
    "tags": ["az extension add --name azure-devops", "az login", "az devops configure", "az devops project", " Clone-Repo"],
    "thumbnails": [
      {
        "type": "image",
        "order": 100,
        "url": "https://raw.githubusercontent.com/pnp/script-samples/main/scripts/azure-devops-clone-all-repositories/assets/preview.png",
        "alt": "Preview of the sample Clone all repositories from Azure DevOps"
      }
    ],
    "authors": [
      {
        "gitHubAccount": "HarminderSethi",
        "company": "",
        "pictureUrl": "https://github.com/HarminderSethi.png",
        "name": "Harminder Singh"
      }
    ],
    "references": [
      {
        "name": "Want to learn more about Azure CLI and the commands",
        "description": "Check out the Azure CLI documentation site to get started and for the reference to the commands.",
        "url": "https://learn.microsoft.com/cli/azure/"
      },
      {
        "name": "Want to learn more about Azure CLI and the commands",
        "description": "Check out the Azure CLI documentation site to get started and for the reference to the commands.",
        "url": "https://learn.microsoft.com/cli/azure/"
      }
    ]
  }
]
